{
  "hash": "2ddd4800",
  "configHash": "60849441",
  "lockfileHash": "0f3d00d1",
  "browserHash": "f12e358d",
  "optimized": {
    "react": {
      "src": "../../node_modules/react/index.js",
      "file": "react.js",
      "fileHash": "2c037778",
      "needsInterop": true
    },
    "react-dom/client": {
      "src": "../../node_modules/react-dom/client.js",
      "file": "react-dom_client.js",
      "fileHash": "fbf7aa38",
      "needsInterop": true
    }
  },
  "chunks": {
    "chunk-KHA5YKM3": {
      "file": "chunk-KHA5YKM3.js"
    }
  }
}